{
  "ok": true,
  "filter": "dn25m",
  "label": "Down 25%+ Monthly",
  "min_cap_b": 1.0,
  "count": 18,
  "stocks": [
    {
      "ticker": "SHAK",
      "company": "Shake Shack, Inc.",
      "industry": "Restaurants",
      "market_cap_b": 2.3,
      "price": 57.01,
      "change_pct": -8.37,
      "dollar_volume": "$160.1M",
      "adr_pct": 7.4,
      "perf_1m": -44.77,
      "perf_3m": -41.03,
      "perf_34d": null,
      "perf_qtd": -41.03,
      "perf_mtd": -44.77,
      "rs_ibd": 4
    },
    {
      "ticker": "XNDU",
      "company": "Xanadu Quantum Technologies Limited",
      "industry": "Computer Processing Hardware",
      "market_cap_b": 4.806,
      "price": 16.93,
      "change_pct": 5.16,
      "dollar_volume": "$104.8M",
      "adr_pct": 17.6,
      "perf_1m": -42.61,
      "perf_3m": 64.37,
      "perf_34d": null,
      "perf_qtd": 64.37,
      "perf_mtd": -42.61,
      "rs_ibd": 80
    },
    {
      "ticker": "UI",
      "company": "Ubiquiti Inc.",
      "industry": "Telecommunications Equipment",
      "market_cap_b": 35.621,
      "price": 588.57,
      "change_pct": 2.28,
      "dollar_volume": "$90.4M",
      "adr_pct": 7.0,
      "perf_1m": -42.47,
      "perf_3m": -24.22,
      "perf_34d": null,
      "perf_qtd": -24.22,
      "perf_mtd": -42.47,
      "rs_ibd": 66
    },
    {
      "ticker": "ABVX",
      "company": "Abivax SA",
      "industry": "Pharmaceuticals: Other",
      "market_cap_b": 10.37,
      "price": 72.5,
      "change_pct": -44.1,
      "dollar_volume": "$252.2M",
      "adr_pct": 13.3,
      "perf_1m": -38.26,
      "perf_3m": -35.23,
      "perf_34d": null,
      "perf_qtd": -35.23,
      "perf_mtd": -38.26,
      "rs_ibd": 99
    },
    {
      "ticker": "ALHC",
      "company": "Alignment Healthcare, Inc.",
      "industry": "Managed Health Care",
      "market_cap_b": 2.82,
      "price": 13.64,
      "change_pct": 2.56,
      "dollar_volume": "$66.0M",
      "adr_pct": 6.9,
      "perf_1m": -35.42,
      "perf_3m": -26.47,
      "perf_34d": null,
      "perf_qtd": -26.47,
      "perf_mtd": -35.42,
      "rs_ibd": 30
    },
    {
      "ticker": "FUTU",
      "company": "Futu Holdings Limited",
      "industry": "Investment Banks/Brokers",
      "market_cap_b": 14.419,
      "price": 101.97,
      "change_pct": -0.86,
      "dollar_volume": "$1.24B",
      "adr_pct": 9.4,
      "perf_1m": -34.39,
      "perf_3m": -30.7,
      "perf_34d": null,
      "perf_qtd": -30.7,
      "perf_mtd": -34.39,
      "rs_ibd": 59
    },
    {
      "ticker": "ZTS",
      "company": "Zoetis Inc.",
      "industry": "Pharmaceuticals: Major",
      "market_cap_b": 32.025,
      "price": 76.39,
      "change_pct": -1.51,
      "dollar_volume": "$556.5M",
      "adr_pct": 4.4,
      "perf_1m": -34.27,
      "perf_3m": -39.33,
      "perf_34d": null,
      "perf_qtd": -39.33,
      "perf_mtd": -34.27,
      "rs_ibd": 4
    },
    {
      "ticker": "PLAB",
      "company": "Photronics, Inc.",
      "industry": "Electronic Production Equipment",
      "market_cap_b": 1.954,
      "price": 33.14,
      "change_pct": 3.98,
      "dollar_volume": "$97.3M",
      "adr_pct": 10.8,
      "perf_1m": -33.02,
      "perf_3m": -8.88,
      "perf_34d": null,
      "perf_qtd": -8.88,
      "perf_mtd": -33.02,
      "rs_ibd": 76
    },
    {
      "ticker": "TMDX",
      "company": "TransMedics Group, Inc.",
      "industry": "Medical Specialties",
      "market_cap_b": 2.366,
      "price": 68.45,
      "change_pct": 1.36,
      "dollar_volume": "$91.7M",
      "adr_pct": 7.0,
      "perf_1m": -32.21,
      "perf_3m": -54.1,
      "perf_34d": null,
      "perf_qtd": -54.1,
      "perf_mtd": -32.21,
      "rs_ibd": 9
    },
    {
      "ticker": "PRIM",
      "company": "Primoris Services Corporation",
      "industry": "Engineering & Construction",
      "market_cap_b": 6.744,
      "price": 124.31,
      "change_pct": 2.36,
      "dollar_volume": "$253.1M",
      "adr_pct": 7.5,
      "perf_1m": -31.57,
      "perf_3m": -17.0,
      "perf_34d": null,
      "perf_qtd": -17.0,
      "perf_mtd": -31.57,
      "rs_ibd": 78
    },
    {
      "ticker": "NKTR",
      "company": "Nektar Therapeutics",
      "industry": "Pharmaceuticals: Major",
      "market_cap_b": 1.979,
      "price": 58.56,
      "change_pct": -8.3,
      "dollar_volume": "$56.9M",
      "adr_pct": 6.3,
      "perf_1m": -31.36,
      "perf_3m": -15.13,
      "perf_34d": null,
      "perf_qtd": -15.13,
      "perf_mtd": -31.36,
      "rs_ibd": 98
    },
    {
      "ticker": "IBP",
      "company": "Installed Building Products, Inc.",
      "industry": "Engineering & Construction",
      "market_cap_b": 5.504,
      "price": 204.3,
      "change_pct": 1.24,
      "dollar_volume": "$87.3M",
      "adr_pct": 5.7,
      "perf_1m": -29.51,
      "perf_3m": -37.4,
      "perf_34d": null,
      "perf_qtd": -37.4,
      "perf_mtd": -29.51,
      "rs_ibd": 70
    },
    {
      "ticker": "WHR",
      "company": "Whirlpool Corporation",
      "industry": "Electronics/Appliances",
      "market_cap_b": 2.658,
      "price": 41.01,
      "change_pct": -3.37,
      "dollar_volume": "$113.3M",
      "adr_pct": 5.7,
      "perf_1m": -26.83,
      "perf_3m": -32.49,
      "perf_34d": null,
      "perf_qtd": -32.49,
      "perf_mtd": -26.83,
      "rs_ibd": 8
    },
    {
      "ticker": "OSIS",
      "company": "OSI Systems, Inc.",
      "industry": "Aerospace & Defense",
      "market_cap_b": 3.495,
      "price": 212.01,
      "change_pct": -0.64,
      "dollar_volume": "$64.1M",
      "adr_pct": 4.7,
      "perf_1m": -26.33,
      "perf_3m": -26.21,
      "perf_34d": null,
      "perf_qtd": -26.21,
      "perf_mtd": -26.33,
      "rs_ibd": 35
    },
    {
      "ticker": "FRPT",
      "company": "Freshpet, Inc.",
      "industry": "Food: Specialty/Candy",
      "market_cap_b": 2.45,
      "price": 49.86,
      "change_pct": 0.89,
      "dollar_volume": "$92.9M",
      "adr_pct": 5.7,
      "perf_1m": -26.0,
      "perf_3m": -40.8,
      "perf_34d": null,
      "perf_qtd": -40.8,
      "perf_mtd": -26.0,
      "rs_ibd": 7
    },
    {
      "ticker": "WIX",
      "company": "Wix.com Ltd.",
      "industry": "Packaged Software",
      "market_cap_b": 3.142,
      "price": 57.07,
      "change_pct": -8.75,
      "dollar_volume": "$118.9M",
      "adr_pct": 9.2,
      "perf_1m": -25.94,
      "perf_3m": -22.18,
      "perf_34d": null,
      "perf_qtd": -22.18,
      "perf_mtd": -25.94,
      "rs_ibd": 4
    },
    {
      "ticker": "BFAM",
      "company": "Bright Horizons Family Solutions Inc.",
      "industry": "Miscellaneous Commercial Services",
      "market_cap_b": 3.211,
      "price": 61.03,
      "change_pct": -6.84,
      "dollar_volume": "$72.8M",
      "adr_pct": 4.9,
      "perf_1m": -25.59,
      "perf_3m": -18.42,
      "perf_34d": null,
      "perf_qtd": -18.42,
      "perf_mtd": -25.59,
      "rs_ibd": 6
    },
    {
      "ticker": "MDLN",
      "company": "Medline Inc.",
      "industry": "Medical Specialties",
      "market_cap_b": 28.066,
      "price": 33.19,
      "change_pct": -7.16,
      "dollar_volume": "$598.0M",
      "adr_pct": 5.4,
      "perf_1m": -25.32,
      "perf_3m": -24.17,
      "perf_34d": null,
      "perf_qtd": -24.17,
      "perf_mtd": -25.32,
      "rs_ibd": 19
    }
  ],
  "spx_benchmarks": {
    "spx_1d": 0.13,
    "spx_1m": 5.68,
    "spx_3m": 10.78,
    "spx_34d": 8.36,
    "spx_qtd": 15.73,
    "spx_mtd": 0.13
  },
  "fetched_at_utc": "2026-06-03T04:31:29+00:00",
  "source": "tv_fallback"
}