{
  "generated_at": "2026-05-07 08:05 ET",
  "phase": "PRE",
  "session": "Pre-Market",
  "assets": {
    "SPY": {
      "label": "S&P 500 ETF",
      "price": 733.83,
      "open": 728.16,
      "high": 734.59,
      "low": 727.82,
      "close": 733.83,
      "prev_open": 721.77,
      "prev_close": 723.77,
      "volume": 53209000,
      "change_pct": 1.39
    },
    "QQQ": {
      "label": "Nasdaq 100 ETF",
      "price": 695.77,
      "open": 687.78,
      "high": 695.93,
      "low": 686.48,
      "close": 695.77,
      "prev_open": 677.96,
      "prev_close": 681.61,
      "volume": 38454700,
      "change_pct": 2.08
    },
    "^VIX": {
      "label": "VIX",
      "price": 17.45,
      "open": 17.53,
      "high": 17.6,
      "low": 17.42,
      "close": 17.45,
      "prev_open": 17.15,
      "prev_close": 17.39,
      "volume": 0,
      "change_pct": 0.35
    },
    "CL=F": {
      "label": "Crude Oil",
      "price": 91.9,
      "open": 96.3,
      "high": 96.48,
      "low": 91.33,
      "close": 91.9,
      "prev_open": 102.7,
      "prev_close": 95.08,
      "volume": 72374,
      "change_pct": -3.34
    },
    "^N225": {
      "label": "Nikkei 225",
      "price": 62833.84,
      "open": 60241.31,
      "high": 63091.14,
      "low": 60213.02,
      "close": 62833.84,
      "prev_open": 59379.12,
      "prev_close": 59513.12,
      "volume": 0,
      "change_pct": 5.58
    },
    "^GDAXI": {
      "label": "DAX",
      "price": 24861.21,
      "open": 24940.36,
      "high": 25021.02,
      "low": 24847.84,
      "close": 24861.21,
      "prev_open": 24636.16,
      "prev_close": 24918.69,
      "volume": 0,
      "change_pct": -0.23
    }
  },
  "fred": {
    "hy_oas": 2.77,
    "yield_curve": 0.49,
    "hy_oas_stale": false,
    "yield_curve_stale": false
  },
  "breadth": {
    "s5fi": 62.1,
    "mmth": 61.6
  },
  "regime": {
    "credit_status": "Complacent",
    "yc_status": "Normal / Steepening",
    "breadth_flush": false,
    "generational_buy_zone": false,
    "reversal": {
      "signal_detected": false,
      "signal_description": "",
      "patterns": {}
    }
  },
  "analysis": {
    "title": "Pre-Market Brief: May 07, 2026",
    "mood_emoji": "🚀",
    "mood": "Risk-On Momentum",
    "narrative": "Global equities demonstrate significant bullish momentum, with Asian markets leading a broad-based rally. Risk appetite remains elevated, driven by strong sentiment despite some commodity weakness.",
    "snapshot_md": "| Asset | Last | % Change | Sentiment |\n|-------|------|----------|-----------|\n| S&P 500 ETF | 733.83 | +1.39% | 📈 |\n| Nasdaq 100 ETF | 695.77 | +2.08% | 📈 |\n| VIX | 17.45 | +0.35% | ➡️ |\n| Crude Oil | 91.90 | -3.34% | 📉 |\n| Nikkei 225 | 62833.84 | +5.58% | 📈 |\n| DAX | 24861.21 | -0.23% | ➡️ |",
    "macro_section": "The high-yield credit spread (BAMLH0A0HYM2) remains complacent at 2.77%, indicating robust institutional risk appetite. Concurrently, the 10Y-2Y yield curve sits at a normal and steepening +0.490, further reinforcing a healthy environment for risk-taking and growth expectations among market participants.",
    "analysis_para1": "The global tape reveals a significant disparity, with the Nikkei 225 surging an impressive +5.58%, while the DAX saw a minor retreat of -0.23%. This strong Asian performance, alongside a notable -3.34% drop in Crude Oil to $91.90, paints a mixed picture, yet US high-yield credit spreads remain stable and complacent at 2.77%. The divergent moves suggest robust equity demand is outweighing commodity-specific concerns or localized European softness, implying a generally positive and resilient risk appetite for US assets.",
    "analysis_para2": "Today's primary flow appears to be driven by a powerful combination of positive sentiment spillover from strong Asian markets and a potential positioning squeeze. The Nikkei's massive +5.58% jump likely triggered a wave of buying across global equity indices, forcing short covering and momentum chasing. This mechanical catalyst fuels the S&P 500 ETF's +1.39% and Nasdaq 100 ETF's +2.08% gains, pushing broad indices higher as bearish bets are unwound and sidelined capital re-engages.",
    "analysis_para3": "Traders should monitor the S&P 500 ETF for follow-through strength, with the previous session's close likely serving as an initial intraday support. A constructive plan involves looking for long entries on any dips towards key hourly moving averages or prior resistance levels that now act as support. The primary risk-off threshold would be a break below the prior day's low, signaling potential exhaustion of the current rally. Today, the focus is on capitalizing on momentum while carefully managing risk below established support zones.",
    "technical_signal": "No reversal pattern confirmed yet. The market exhibits strong bullish momentum with 62.1% of stocks above their 50-day moving average and 61.6% above their 200-day, indicating broad participation. Watch for any intraday divergences or a breakdown of key support levels as signs of potential shifts.",
    "ticker_intel": {
      "a_grade": [
        {
          "ticker": "GOOGL",
          "company": "Alphabet Inc.",
          "reason": "Announces breakthrough AI partnership with major automotive manufacturer, signaling significant revenue expansion opportunities."
        },
        {
          "ticker": "AMZN",
          "company": "Amazon.com, Inc.",
          "reason": "Reports significant Q1 earnings beat with strong cloud growth guidance, reaffirming AWS's market dominance and profitability."
        }
      ],
      "c_grade": [
        {
          "ticker": "NVDA",
          "company": "NVIDIA Corporation",
          "reason": "Continues to benefit from ongoing AI infrastructure buildout and strong speculative flow, sustaining elevated valuation narratives."
        }
      ]
    }
  }
}