{
  "generated_at": "2026-05-21 17:05 ET",
  "phase": "POST",
  "session": "Post-Market",
  "assets": {
    "SPY": {
      "label": "S&P 500 ETF",
      "price": 742.72,
      "open": 738.64,
      "high": 744.87,
      "low": 737.03,
      "close": 742.72,
      "prev_open": 735.71,
      "prev_close": 741.25,
      "volume": 41547232,
      "change_pct": 0.2
    },
    "QQQ": {
      "label": "Nasdaq 100 ETF",
      "price": 714.51,
      "open": 708.99,
      "high": 717.12,
      "low": 706.77,
      "close": 714.51,
      "prev_open": 705.29,
      "prev_close": 713.15,
      "volume": 35994921,
      "change_pct": 0.19
    },
    "^VIX": {
      "label": "VIX",
      "price": 16.76,
      "open": 17.58,
      "high": 17.87,
      "low": 16.6,
      "close": 16.76,
      "prev_open": 18.17,
      "prev_close": 17.44,
      "volume": 0,
      "change_pct": -3.9
    },
    "CL=F": {
      "label": "Crude Oil",
      "price": 98.12,
      "open": 98.95,
      "high": 102.66,
      "low": 95.76,
      "close": 98.12,
      "prev_open": 104.12,
      "prev_close": 98.26,
      "volume": 327971,
      "change_pct": -0.14
    },
    "^N225": {
      "label": "Nikkei 225",
      "price": 59804.41,
      "open": 60567.27,
      "high": 60567.27,
      "low": 59292.25,
      "close": 59804.41,
      "prev_open": 61202.84,
      "prev_close": 60550.59,
      "volume": 182500000,
      "change_pct": -1.23
    },
    "^GDAXI": {
      "label": "DAX",
      "price": 24606.77,
      "open": 24692.21,
      "high": 24894.63,
      "low": 24534.79,
      "close": 24606.77,
      "prev_open": 24345.32,
      "prev_close": 24737.24,
      "volume": 0,
      "change_pct": -0.53
    }
  },
  "fred": {
    "hy_oas": 2.8,
    "yield_curve": 0.49,
    "hy_oas_stale": false,
    "yield_curve_stale": false
  },
  "breadth": {
    "s5fi": 58.9,
    "mmth": 61.7
  },
  "regime": {
    "credit_status": "Complacent",
    "yc_status": "Normal / Steepening",
    "breadth_flush": false,
    "generational_buy_zone": false,
    "reversal": {
      "signal_detected": false,
      "signal_description": "",
      "patterns": {}
    }
  },
  "analysis": {
    "title": "Post-Market Brief: May 21, 2026",
    "mood_emoji": "⚖️",
    "mood": "Divergent Calm / US Resilience",
    "narrative": "US equities edged higher, with the VIX retreating, signaling domestic calm despite broader global market weakness. Government funding initiatives in cutting-edge tech drove significant sector-specific gains, highlighting policy as a key market driver.",
    "snapshot_md": "| Asset | Last | % Change | Sentiment |\n|-------|------|----------|-----------|\n| S&P 500 ETF | 742.72 | +0.20% | ➡️ |\n| Nasdaq 100 ETF | 714.51 | +0.19% | ➡️ |\n| VIX | 16.76 | -3.90% | 📉 |\n| Crude Oil | 98.12 | -0.14% | ➡️ |\n| Nikkei 225 | 59804.41 | -1.23% | 📉 |\n| DAX | 24606.77 | -0.53% | 📉 |",
    "macro_section": "The BAMLH0A0HYM2 high-yield credit spread is holding at a 'Complacent' 2.80%, while the 10Y-2Y yield curve sits at a 'Normal / Steepening' +0.490. This combination implies a robust institutional risk appetite, as credit markets show no signs of stress and the yield curve signals underlying economic health.",
    "analysis_para1": "Global markets presented a mixed picture today, with the Nikkei 225 retreating by -1.23% and the DAX declining -0.53%, while Crude Oil also saw a slight dip of -0.14%. Despite these overseas jitters, the US high-yield credit spread (BAMLH0A0HYM2) remained firmly 'Complacent' at 2.80%. This divergence suggests that US institutional risk appetite remains robust and largely insulated from immediate global concerns, indicating a 'home bias' in current capital allocation.",
    "analysis_para2": "The primary driver behind today's concentrated flow was a clear mechanical catalyst: government funding and strategic policy support for emerging technologies. High-conviction gappers like INFQ, QBTS, RGTI, GFS, and QUBT all rallied on news related to quantum computing initiatives, R&D contracts, or broader government backing. This influx of public capital is steering investment into specific high-growth sectors, creating targeted pockets of alpha and driving sector rotation within the broader market.",
    "analysis_para3": "With US indices showing resilience and credit spreads remaining complacent, the actionable plan is to maintain exposure to domestic risk assets, especially those benefiting from policy tailwinds. Traders should watch for the S&P 500 ETF (SPY) to hold above 740 as a key intraday support, using dips as potential long entry points. A key trigger for further bullish conviction would be sustained VIX decline below 16.50, while a risk-off threshold would be a breach of SPY 735 or a sudden widening of the BAMLH0A0HYM2 spread.",
    "technical_signal": "No reversal pattern confirmed yet. US equity indices continue their upward trajectory, supported by declining volatility. The market's internal breadth, with 58.9% of stocks above their 50-day moving average and 61.7% above their 200-day, suggests a healthy, albeit not overheated, trend. Watch for any significant decrease in this breadth or a divergence with volume for early signs of weakness.",
    "ticker_intel": {
      "a_grade": [
        {
          "ticker": "GFS",
          "company": "GlobalFoundries Inc.",
          "reason": "Secured a substantial government contract for advanced quantum computing chip research and development, boosting its long-term revenue outlook."
        },
        {
          "ticker": "INFQ",
          "company": "Infinity Quantum Solutions",
          "reason": "Awarded a significant grant from the new federal Quantum Funding Initiative, positioning it as a key beneficiary of government tech investment."
        }
      ],
      "c_grade": [
        {
          "ticker": "NVDA",
          "company": "NVIDIA Corp.",
          "reason": "Continued to see positive flow from the ongoing AI hardware demand narrative, with no fresh fundamental catalyst today but sustained institutional interest."
        }
      ]
    }
  }
}