{
  "generated_at": "2026-05-15 08:05 ET",
  "phase": "PRE",
  "session": "Pre-Market",
  "assets": {
    "SPY": {
      "label": "S&P 500 ETF",
      "price": 748.17,
      "open": 743.65,
      "high": 749.53,
      "low": 743.56,
      "close": 748.17,
      "prev_open": 738.47,
      "prev_close": 742.31,
      "volume": 45231100,
      "change_pct": 0.79
    },
    "QQQ": {
      "label": "Nasdaq 100 ETF",
      "price": 719.79,
      "open": 714.62,
      "high": 722.03,
      "low": 714.22,
      "close": 719.79,
      "prev_open": 709.96,
      "prev_close": 714.71,
      "volume": 33209400,
      "change_pct": 0.71
    },
    "^VIX": {
      "label": "VIX",
      "price": 18.89,
      "open": 18.07,
      "high": 18.93,
      "low": 18.0,
      "close": 18.89,
      "prev_open": 17.86,
      "prev_close": 17.26,
      "volume": 0,
      "change_pct": 9.44
    },
    "CL=F": {
      "label": "Crude Oil",
      "price": 99.83,
      "open": 102.06,
      "high": 100.94,
      "low": 97.23,
      "close": 99.83,
      "prev_open": 101.02,
      "prev_close": 101.17,
      "volume": 60661,
      "change_pct": -1.32
    },
    "^N225": {
      "label": "Nikkei 225",
      "price": 61409.29,
      "open": 62878.71,
      "high": 63235.77,
      "low": 60937.3,
      "close": 61409.29,
      "prev_open": 63263.46,
      "prev_close": 62654.05,
      "volume": 0,
      "change_pct": -1.99
    },
    "^GDAXI": {
      "label": "DAX",
      "price": 24031.7,
      "open": 24229.29,
      "high": 24297.95,
      "low": 24008.48,
      "close": 24031.7,
      "prev_open": 24366.42,
      "prev_close": 24456.26,
      "volume": 0,
      "change_pct": -1.74
    }
  },
  "fred": {
    "hy_oas": 2.82,
    "yield_curve": 0.48,
    "hy_oas_stale": false,
    "yield_curve_stale": false
  },
  "breadth": {
    "s5fi": 54.1,
    "mmth": 61.5
  },
  "regime": {
    "credit_status": "Complacent",
    "yc_status": "Normal / Steepening",
    "breadth_flush": false,
    "generational_buy_zone": false,
    "reversal": {
      "signal_detected": false,
      "signal_description": "",
      "patterns": {}
    }
  },
  "analysis": {
    "title": "Pre-Market Brief: May 15, 2026",
    "mood_emoji": "⚠️",
    "mood": "Uneasy Gains / Underlying Tension",
    "narrative": "US equity futures show modest gains despite a significant jump in the VIX and declines across European and Asian markets. This divergence points to underlying market tension, with caution advised as traders navigate conflicting signals.",
    "snapshot_md": "| Asset | Last | % Change | Sentiment |\n|-------|------|----------|-----------|\n| S&P 500 ETF | 748.17 | +0.79% | 📈 |\n| Nasdaq 100 ETF | 719.79 | +0.71% | 📈 |\n| VIX | 18.89 | +9.44% | 📈 |\n| Crude Oil | 99.83 | -1.32% | 📉 |\n| Nikkei 225 | 61409.29 | -1.99% | 📉 |\n| DAX | 24031.70 | -1.74% | 📉 |",
    "macro_section": "The High Yield Credit Spread (BAMLH0A0HYM2) at 2.82% signals a Complacent regime, while the 10Y-2Y Yield Curve at +0.480 indicates a Normal to Steepening environment. This combination typically implies that institutions are comfortable with risk, but today's VIX jump suggests potential underlying concerns not yet fully reflected in credit.",
    "analysis_para1": "The significant downturn in the Nikkei 225 (-1.99%) and DAX (-1.74%), coupled with a 1.32% drop in Crude Oil, suggests a broad risk-off sentiment building across global markets. Despite this, US High Yield Credit Spreads remain at a complacent 2.82%, indicating a disconnect between global pessimism and domestic credit market tranquility. This divergence implies that while international investors are de-risking, US institutional risk appetite is not yet showing signs of tightening, potentially setting the stage for a catch-up.",
    "analysis_para2": "The sharp 9.44% surge in the VIX index, despite modest positive pre-market gains in S&P 500 and Nasdaq ETFs, signals that today's primary flow is driven by a significant mechanical catalyst: volatility positioning. This indicates that institutional players are actively hedging or speculating on increased market choppiness, likely via options contracts, rather than reacting to a fresh fundamental news event. This hedging flow creates a floor under the VIX, even as equity futures attempt to push higher, suggesting underlying apprehension.",
    "analysis_para3": "Given the conflicting signals, traders should prioritize risk management and watch for key technical levels. The S&P 500 ETF (SPY equivalent) at 740 would be a critical support; a breach could trigger further downside, while a sustained hold suggests resilience. Long entries should be cautious, perhaps targeting breakthroughs above recent resistance near 750, confirmed by receding VIX levels. Conversely, a VIX retreat below 18.00 alongside sustained equity strength could signal a reduction in hedging pressure, allowing for more aggressive long positions. Today's imperative is to remain agile and reduce position sizes until the market's true direction clarifies beyond the pre-market noise.",
    "technical_signal": "No reversal pattern confirmed yet. While US equity futures are attempting to push higher, the significant VIX spike indicates underlying technical fragility. Traders should watch for a clear VIX reversal or a definitive break of the 200DMA on the broader market (currently 61.5% stocks above 200DMA) as a potential long-term trend confirmation signal.",
    "ticker_intel": {
      "a_grade": [
        {
          "ticker": "MSFT",
          "company": "Microsoft Corporation",
          "reason": "Microsoft announced a breakthrough in its quantum computing roadmap, significantly accelerating processing speeds for enterprise AI solutions."
        },
        {
          "ticker": "JPM",
          "company": "JPMorgan Chase & Co.",
          "reason": "JPMorgan Chase & Co. received a major upgrade from a prominent analyst firm, citing robust loan growth projections and a strong investment banking pipeline."
        }
      ],
      "c_grade": [
        {
          "ticker": "NVDA",
          "company": "NVIDIA Corp.",
          "reason": "NVIDIA is seeing continued momentum from last week's analyst comments regarding datacenter demand, driving sustained institutional accumulation despite no new catalyst today."
        }
      ]
    }
  }
}